{"name":"Json-c","tagline":"Official code repository for json-c.  See the wiki for release tarballs for download.","body":"Building on Unix with git, gcc and autotools\r\n\r\nHome page for json-c:\r\n  https://github.com/json-c/json-c/wiki\r\n\r\n  Caution: do NOT use sources from svn.metaparadigm.com, they are old.\r\n\r\nPrerequisites:\r\n\tgcc (or another C compiler)\r\n\tlibtool\r\n\r\n\tIf you're not using a release tarball, you'll also need:\r\n\tautoconf (autoreconf)\r\n\tautomake\r\n\r\nGithub repo for json-c:\r\n  https://github.com/json-c/json-c\r\n\r\n    $ git clone https://github.com/json-c/json-c.git\r\n    $ cd json-c\r\n    $ sh autogen.sh\r\n\r\nThen \r\n\r\n    $ ./configure\r\n    $ make\r\n    $ make install\r\n\r\nTo build and run the test programs run \r\n\r\n    $ make check\r\n\r\nLinking to libjson-c\r\n\r\nIf your system has pkgconfig then you can just add this to your makefile\r\n\r\nCFLAGS += $(shell pkg-config --cflags json-c)\r\nLDFLAGS += $(shell pkg-config --libs json-c)\r\n\r\nWithout pkgconfig, you would do something like this:\r\n\r\nJSON_C_DIR=/path/to/json_c/install\r\nCFLAGS += -I$(JSON_C_DIR)/include/json-c\r\nLDFLAGS+= -L$(JSON_C_DIR)/lib -ljson-c\r\n","google":"","note":"Don't delete this file! It's used internally to help with page regeneration."}